<?xml version="1.0" encoding="utf-8"?>
<TextureAtlas imagePath="nonsense_events.png">
	<!-- Created with Adobe Animate version 19.2.1.408 -->
	<!-- http://www.adobe.com/products/animate.html -->
	<SubTexture name="boredEvent0000" x="5" y="5" width="286" height="659" frameX="-1" frameY="-11" frameWidth="288" frameHeight="670"/>
	<SubTexture name="boredEvent0001" x="5" y="5" width="286" height="659" frameX="-1" frameY="-11" frameWidth="288" frameHeight="670"/>
	<SubTexture name="boredEvent0002" x="296" y="5" width="288" height="660" frameX="0" frameY="-10" frameWidth="288" frameHeight="670"/>
	<SubTexture name="boredEvent0003" x="296" y="5" width="288" height="660" frameX="0" frameY="-10" frameWidth="288" frameHeight="670"/>
	<SubTexture name="boredEvent0004" x="296" y="5" width="288" height="660" frameX="0" frameY="-10" frameWidth="288" frameHeight="670"/>
	<SubTexture name="boredEvent0005" x="296" y="5" width="288" height="660" frameX="0" frameY="-10" frameWidth="288" frameHeight="670"/>
	<SubTexture name="boredEvent0006" x="589" y="5" width="286" height="670" frameX="-2" frameY="0" frameWidth="288" frameHeight="670"/>
	<SubTexture name="boredEvent0007" x="589" y="5" width="286" height="670" frameX="-2" frameY="0" frameWidth="288" frameHeight="670"/>
	<SubTexture name="boredEvent0008" x="880" y="5" width="285" height="669" frameX="-3" frameY="-1" frameWidth="288" frameHeight="670"/>
	<SubTexture name="boredEvent0009" x="880" y="5" width="285" height="669" frameX="-3" frameY="-1" frameWidth="288" frameHeight="670"/>
	<SubTexture name="boredEvent0010" x="880" y="5" width="285" height="669" frameX="-3" frameY="-1" frameWidth="288" frameHeight="670"/>
	<SubTexture name="boredEvent0011" x="1170" y="5" width="284" height="669" frameX="-4" frameY="-1" frameWidth="288" frameHeight="670"/>
	<SubTexture name="boredEvent0012" x="1170" y="5" width="284" height="669" frameX="-4" frameY="-1" frameWidth="288" frameHeight="670"/>
	<SubTexture name="boredEvent0013" x="1170" y="5" width="284" height="669" frameX="-4" frameY="-1" frameWidth="288" frameHeight="670"/>
	<SubTexture name="boredEvent0014" x="1170" y="5" width="284" height="669" frameX="-4" frameY="-1" frameWidth="288" frameHeight="670"/>
	<SubTexture name="boredEvent0015" x="1170" y="5" width="284" height="669" frameX="-4" frameY="-1" frameWidth="288" frameHeight="670"/>
	<SubTexture name="boredEvent0016" x="1170" y="5" width="284" height="669" frameX="-4" frameY="-1" frameWidth="288" frameHeight="670"/>
	<SubTexture name="boredEvent0017" x="1170" y="5" width="284" height="669" frameX="-4" frameY="-1" frameWidth="288" frameHeight="670"/>
	<SubTexture name="boredEvent0018" x="1170" y="5" width="284" height="669" frameX="-4" frameY="-1" frameWidth="288" frameHeight="670"/>
	<SubTexture name="boredEvent0019" x="1170" y="5" width="284" height="669" frameX="-4" frameY="-1" frameWidth="288" frameHeight="670"/>
	<SubTexture name="boredEvent0020" x="1170" y="5" width="284" height="669" frameX="-4" frameY="-1" frameWidth="288" frameHeight="670"/>
	<SubTexture name="boredEvent0021" x="1170" y="5" width="284" height="669" frameX="-4" frameY="-1" frameWidth="288" frameHeight="670"/>
	<SubTexture name="boredEvent0022" x="1170" y="5" width="284" height="669" frameX="-4" frameY="-1" frameWidth="288" frameHeight="670"/>
	<SubTexture name="boredEvent0023" x="1170" y="5" width="284" height="669" frameX="-4" frameY="-1" frameWidth="288" frameHeight="670"/>
	<SubTexture name="boredEvent0024" x="1170" y="5" width="284" height="669" frameX="-4" frameY="-1" frameWidth="288" frameHeight="670"/>
	<SubTexture name="boredEvent0025" x="1170" y="5" width="284" height="669" frameX="-4" frameY="-1" frameWidth="288" frameHeight="670"/>
	<SubTexture name="boredEvent0026" x="1170" y="5" width="284" height="669" frameX="-4" frameY="-1" frameWidth="288" frameHeight="670"/>
	<SubTexture name="boredEvent0027" x="1170" y="5" width="284" height="669" frameX="-4" frameY="-1" frameWidth="288" frameHeight="670"/>
	<SubTexture name="boredEvent0028" x="1170" y="5" width="284" height="669" frameX="-4" frameY="-1" frameWidth="288" frameHeight="670"/>
	<SubTexture name="boredEvent0029" x="1170" y="5" width="284" height="669" frameX="-4" frameY="-1" frameWidth="288" frameHeight="670"/>
	<SubTexture name="boredEvent0030" x="1170" y="5" width="284" height="669" frameX="-4" frameY="-1" frameWidth="288" frameHeight="670"/>
	<SubTexture name="boredEvent0031" x="1170" y="5" width="284" height="669" frameX="-4" frameY="-1" frameWidth="288" frameHeight="670"/>
	<SubTexture name="boredEvent0032" x="1170" y="5" width="284" height="669" frameX="-4" frameY="-1" frameWidth="288" frameHeight="670"/>
	<SubTexture name="boredEvent0033" x="1170" y="5" width="284" height="669" frameX="-4" frameY="-1" frameWidth="288" frameHeight="670"/>
	<SubTexture name="boredEvent0034" x="1170" y="5" width="284" height="669" frameX="-4" frameY="-1" frameWidth="288" frameHeight="670"/>
	<SubTexture name="boredEvent0035" x="1170" y="5" width="284" height="669" frameX="-4" frameY="-1" frameWidth="288" frameHeight="670"/>
	<SubTexture name="boredEvent0036" x="1170" y="5" width="284" height="669" frameX="-4" frameY="-1" frameWidth="288" frameHeight="670"/>
	<SubTexture name="sweatEvent0000" x="1459" y="5" width="283" height="648" frameX="0" frameY="-20" frameWidth="283" frameHeight="668"/>
	<SubTexture name="sweatEvent0001" x="1459" y="5" width="283" height="648" frameX="0" frameY="-20" frameWidth="283" frameHeight="668"/>
	<SubTexture name="sweatEvent0002" x="1747" y="5" width="279" height="651" frameX="-4" frameY="-17" frameWidth="283" frameHeight="668"/>
	<SubTexture name="sweatEvent0003" x="1747" y="5" width="279" height="651" frameX="-4" frameY="-17" frameWidth="283" frameHeight="668"/>
	<SubTexture name="sweatEvent0004" x="5" y="680" width="278" height="653" frameX="-5" frameY="-15" frameWidth="283" frameHeight="668"/>
	<SubTexture name="sweatEvent0005" x="5" y="680" width="278" height="653" frameX="-5" frameY="-15" frameWidth="283" frameHeight="668"/>
	<SubTexture name="sweatEvent0006" x="288" y="680" width="273" height="668" frameX="-10" frameY="0" frameWidth="283" frameHeight="668"/>
	<SubTexture name="sweatEvent0007" x="288" y="680" width="273" height="668" frameX="-10" frameY="0" frameWidth="283" frameHeight="668"/>
	<SubTexture name="sweatEvent0008" x="566" y="680" width="274" height="665" frameX="-9" frameY="-3" frameWidth="283" frameHeight="668"/>
	<SubTexture name="sweatEvent0009" x="566" y="680" width="274" height="665" frameX="-9" frameY="-3" frameWidth="283" frameHeight="668"/>
	<SubTexture name="sweatEvent0010" x="566" y="680" width="274" height="665" frameX="-9" frameY="-3" frameWidth="283" frameHeight="668"/>
	<SubTexture name="sweatEvent0011" x="845" y="680" width="275" height="664" frameX="-8" frameY="-4" frameWidth="283" frameHeight="668"/>
	<SubTexture name="sweatEvent0012" x="845" y="680" width="275" height="664" frameX="-8" frameY="-4" frameWidth="283" frameHeight="668"/>
	<SubTexture name="sweatEvent0013" x="845" y="680" width="275" height="664" frameX="-8" frameY="-4" frameWidth="283" frameHeight="668"/>
	<SubTexture name="sweatEvent0014" x="845" y="680" width="275" height="664" frameX="-8" frameY="-4" frameWidth="283" frameHeight="668"/>
	<SubTexture name="sweatEvent0015" x="845" y="680" width="275" height="664" frameX="-8" frameY="-4" frameWidth="283" frameHeight="668"/>
	<SubTexture name="sweatEvent0016" x="845" y="680" width="275" height="664" frameX="-8" frameY="-4" frameWidth="283" frameHeight="668"/>
	<SubTexture name="sweatEvent0017" x="845" y="680" width="275" height="664" frameX="-8" frameY="-4" frameWidth="283" frameHeight="668"/>
	<SubTexture name="sweatEvent0018" x="845" y="680" width="275" height="664" frameX="-8" frameY="-4" frameWidth="283" frameHeight="668"/>
	<SubTexture name="sweatEvent0019" x="845" y="680" width="275" height="664" frameX="-8" frameY="-4" frameWidth="283" frameHeight="668"/>
	<SubTexture name="sweatEvent0020" x="845" y="680" width="275" height="664" frameX="-8" frameY="-4" frameWidth="283" frameHeight="668"/>
	<SubTexture name="sweatEvent0021" x="845" y="680" width="275" height="664" frameX="-8" frameY="-4" frameWidth="283" frameHeight="668"/>
	<SubTexture name="sweatEvent0022" x="845" y="680" width="275" height="664" frameX="-8" frameY="-4" frameWidth="283" frameHeight="668"/>
	<SubTexture name="sweatEvent0023" x="845" y="680" width="275" height="664" frameX="-8" frameY="-4" frameWidth="283" frameHeight="668"/>
	<SubTexture name="sweatEvent0024" x="845" y="680" width="275" height="664" frameX="-8" frameY="-4" frameWidth="283" frameHeight="668"/>
	<SubTexture name="sweatEvent0025" x="845" y="680" width="275" height="664" frameX="-8" frameY="-4" frameWidth="283" frameHeight="668"/>
	<SubTexture name="sweatEvent0026" x="845" y="680" width="275" height="664" frameX="-8" frameY="-4" frameWidth="283" frameHeight="668"/>
	<SubTexture name="sweatEvent0027" x="845" y="680" width="275" height="664" frameX="-8" frameY="-4" frameWidth="283" frameHeight="668"/>
	<SubTexture name="sweatEvent0028" x="845" y="680" width="275" height="664" frameX="-8" frameY="-4" frameWidth="283" frameHeight="668"/>
	<SubTexture name="sweatEvent0029" x="845" y="680" width="275" height="664" frameX="-8" frameY="-4" frameWidth="283" frameHeight="668"/>
	<SubTexture name="sweatEvent0030" x="845" y="680" width="275" height="664" frameX="-8" frameY="-4" frameWidth="283" frameHeight="668"/>
	<SubTexture name="sweatEvent0031" x="845" y="680" width="275" height="664" frameX="-8" frameY="-4" frameWidth="283" frameHeight="668"/>
	<SubTexture name="sweatEvent0032" x="845" y="680" width="275" height="664" frameX="-8" frameY="-4" frameWidth="283" frameHeight="668"/>
	<SubTexture name="sweatEvent0033" x="845" y="680" width="275" height="664" frameX="-8" frameY="-4" frameWidth="283" frameHeight="668"/>
	<SubTexture name="sweatEvent0034" x="845" y="680" width="275" height="664" frameX="-8" frameY="-4" frameWidth="283" frameHeight="668"/>
	<SubTexture name="sweatEvent0035" x="845" y="680" width="275" height="664" frameX="-8" frameY="-4" frameWidth="283" frameHeight="668"/>
	<SubTexture name="sweatEvent0036" x="845" y="680" width="275" height="664" frameX="-8" frameY="-4" frameWidth="283" frameHeight="668"/>
	<SubTexture name="sweatEvent0037" x="845" y="680" width="275" height="664" frameX="-8" frameY="-4" frameWidth="283" frameHeight="668"/>
	<SubTexture name="sweatEvent0038" x="845" y="680" width="275" height="664" frameX="-8" frameY="-4" frameWidth="283" frameHeight="668"/>
	<SubTexture name="sweatEvent0039" x="845" y="680" width="275" height="664" frameX="-8" frameY="-4" frameWidth="283" frameHeight="668"/>
	<SubTexture name="sweatEvent0040" x="845" y="680" width="275" height="664" frameX="-8" frameY="-4" frameWidth="283" frameHeight="668"/>
</TextureAtlas>
